{
  "$schema": "./code-gen-config.schema.json",
  "CodeGenConfig": {
    "Models": {
      "Defaults": {
        "Properties": [
          {
            "Name": "Id",
            "Type": "Guid",
            "Key": true
          },
          {
            "Name": "CreatedBy",
            "Type": "Guid",
            "AuditCreatedBy": true
          },
          {
            "Name": "DateCreated",
            "Type": "DateTime",
            "AuditDateCreated": true
          },
          {
            "Name": "ModifiedBy",
            "Type": "Guid?",
            "AuditModifiedBy": true
          },
          {
            "Name": "DateModified",
            "Type": "DateTime?",
            "AuditDateModified": true
          },
          {
            "Name": "Deleted",
            "Type": "bool",
            "AuditDeleted": true
          }
        ]
      },
      "List": [
        {
          "Name": "Account",
          "Audit": true,
          "Properties": [
            {
              "Name": "Name",
              "Type": "string",
              "Required": true
            },
            {
              "Name": "Description",
              "Type": "string"
            },
            {
              "Name": "Telephone",
              "Type": "string"
            },
            {
              "Name": "Email",
              "Type": "string"
            },
            {
              "Name": "Website",
              "Type": "string"
            },
            {
              "Name": "VAT",
              "Type": "string"
            }
          ]
        },
        {
          "Name": "Contact",
          "Audit": true,
          "Properties": [
            {
              "Name": "FirstName",
              "Type": "string",
              "Required": true
            },
            {
              "Name": "LastName",
              "Type": "string",
              "Required": true
            },
            {
              "Name": "Telephone",
              "Type": "string"
            },
            {
              "Name": "Email",
              "Type": "string"
            }
          ]
        }
      ]
    },
    "Paths": {
      "Output": "_Output"
    }
  }
}
